tests/__init__.py
tests/credit.csv
tests/house-votes-84.csv
tests/mushroom.csv
tests/test_base.py
tests/test_discretize.py
tests/test_fit.py
tests/test_interpret.py
tests/test_predict_score.py
tests/test_preprocess.py
tests/test_sklearn.py
tests/test_sme.py
tests/wine.csv
wittgenstein/__init__.py
wittgenstein/abstract_ruleset_classifier copy.py
wittgenstein/abstract_ruleset_classifier.py
wittgenstein/base.py
wittgenstein/base_functions.py
wittgenstein/catnap.py
wittgenstein/check.py
wittgenstein/depr_discretize.py
wittgenstein/discretize.py
wittgenstein/interpret.py
wittgenstein/irep.py
wittgenstein/preprocess.py
wittgenstein/ripper.py
wittgenstein/utils.py
wittgenstein/wittgenstein.py
wittgenstein-0.3.4.dist-info/LICENSE
wittgenstein-0.3.4.dist-info/METADATA
wittgenstein-0.3.4.dist-info/WHEEL
wittgenstein-0.3.4.dist-info/top_level.txt
wittgenstein-0.3.4.dist-info/RECORD
