Metadata-Version: 2.1
Name: wittgenstein
Version: 0.3.4
Summary: Ruleset covering algorithms for explainable machine learning
Home-page: https://github.com/imoscovitz/wittgenstein
Author: Ilan Moscovitz
Author-email: ilan.moscovitz@gmail.com
Keywords: Classification,Decision Rule,Machine Learning,Explainable Machine Learning,Data Science,Machine Learning Interpretability,Transparent Machine Learning,ML,Ruleset
Classifier: Programming Language :: Python
Classifier: Programming Language :: Python :: 3.6
Classifier: Programming Language :: Python :: 3.7
Classifier: Programming Language :: Python :: 3.8
Classifier: Programming Language :: Python :: 3.9
License-File: LICENSE
Requires-Dist: pandas
Requires-Dist: numpy
